yule/__init__.py
yule/colors.py
yule/const.py
yule/log_file.py
yule/yulelog.py
yule-0.0.5.dist-info/LICENSE
yule-0.0.5.dist-info/METADATA
yule-0.0.5.dist-info/WHEEL
yule-0.0.5.dist-info/top_level.txt
yule-0.0.5.dist-info/RECORD
