Metadata-Version: 2.1
Name: yule
Version: 0.0.5
Summary: A logging package for python
Home-page: https://github.com/deancolten/yule
Author: Colten Dean
Author-email: coltenrdean@gmail.com
License: UNKNOWN
Platform: UNKNOWN
Classifier: License :: OSI Approved :: GNU General Public License v3 (GPLv3)
Classifier: Programming Language :: Python :: 3
Classifier: Programming Language :: Python :: 3.9
Classifier: Operating System :: OS Independent
Classifier: Topic :: System :: Logging
Requires-Dist: colorama
